MANIFEST.in
setup.py
pandanas/__init__.py
pandanas/exceptions.py
pandanas.egg-info/PKG-INFO
pandanas.egg-info/SOURCES.txt
pandanas.egg-info/dependency_links.txt
pandanas.egg-info/requires.txt
pandanas.egg-info/top_level.txt
pandanas/daemon/__init__.py
pandanas/daemon/generic.py
pandanas/daemon/tools.py
pandanas/daemon/core/__init__.py
pandanas/daemon/core/base.py
pandanas/daemon/core/mixins.py
pandanas/worker_units/__init__.py