Metadata-Version: 1.0
Name: pandanas
Version: 0.0.2
Summary: Micro framework for fast building unix daemon application carcass.
Home-page: https://github.com/6reduk/pandanas
Author: Shestakov Dmitriy
Author-email: 6reduk@gmail.com
License: LICENSE.txt
Platform: UNKNOWN
